{"20220914_1207_0700F136_PIC_150_CAM_2.xml.pi.jpg1442120":{"filename":"20220914_1207_0700F136_PIC_150_CAM_2.xml.pi.jpg","size":1442120,"regions":[{"shape_attributes":{"name":"rect","x":590,"y":599,"width":700,"height":507},"region_attributes":{}},{"shape_attributes":{"name":"circle","cx":1174,"cy":1666,"r":354},"region_attributes":{}},{"shape_attributes":{"name":"ellipse","cx":3231,"cy":1241,"rx":428,"ry":382,"theta":0},"region_attributes":{}},{"shape_attributes":{"name":"polygon","all_points_x":[1427,1357,1335,1476,1849,2075,2096,1448,1421],"all_points_y":[104,306,471,675,770,486,138,21,116]},"region_attributes":{}},{"shape_attributes":{"name":"ellipse","cx":2133,"cy":1773,"rx":193,"ry":229,"theta":0},"region_attributes":{}}],"file_attributes":{}}}