{"20230802_142757.jpg9346524":{"filename":"20230802_142757.jpg","size":9346524,"regions":[{"shape_attributes":{"name":"circle","cx":2204,"cy":720,"r":96},"region_attributes":{}},{"shape_attributes":{"name":"circle","cx":2114,"cy":834,"r":103},"region_attributes":{}},{"shape_attributes":{"name":"circle","cx":1743,"cy":1173,"r":127},"region_attributes":{}},{"shape_attributes":{"name":"circle","cx":1593,"cy":1162,"r":123},"region_attributes":{}},{"shape_attributes":{"name":"circle","cx":1813,"cy":2110,"r":109.905},"region_attributes":{}},{"shape_attributes":{"name":"circle","cx":1878,"cy":2051,"r":94},"region_attributes":{}},{"shape_attributes":{"name":"circle","cx":1714,"cy":2009,"r":76},"region_attributes":{}},{"shape_attributes":{"name":"circle","cx":1843,"cy":2297,"r":106},"region_attributes":{}},{"shape_attributes":{"name":"circle","cx":1651,"cy":2439,"r":86},"region_attributes":{}},{"shape_attributes":{"name":"circle","cx":719,"cy":2245,"r":76},"region_attributes":{}},{"shape_attributes":{"name":"circle","cx":576,"cy":2236,"r":82},"region_attributes":{}},{"shape_attributes":{"name":"circle","cx":679,"cy":2276,"r":64},"region_attributes":{}},{"shape_attributes":{"name":"circle","cx":967,"cy":1915,"r":87},"region_attributes":{}},{"shape_attributes":{"name":"circle","cx":1050,"cy":1851,"r":68},"region_attributes":{}},{"shape_attributes":{"name":"circle","cx":997,"cy":1808,"r":62},"region_attributes":{}},{"shape_attributes":{"name":"circle","cx":917,"cy":1842,"r":59},"region_attributes":{}},{"shape_attributes":{"name":"circle","cx":919,"cy":2909,"r":124},"region_attributes":{}},{"shape_attributes":{"name":"circle","cx":1133,"cy":2897,"r":121},"region_attributes":{}},{"shape_attributes":{"name":"circle","cx":1365,"cy":3848,"r":122.909},"region_attributes":{}},{"shape_attributes":{"name":"circle","cx":1521,"cy":2703,"r":110},"region_attributes":{}},{"shape_attributes":{"name":"circle","cx":804,"cy":275,"r":27},"region_attributes":{}},{"shape_attributes":{"name":"circle","cx":835,"cy":241,"r":32},"region_attributes":{}},{"shape_attributes":{"name":"circle","cx":1922,"cy":41,"r":32},"region_attributes":{}},{"shape_attributes":{"name":"circle","cx":1961,"cy":58,"r":31},"region_attributes":{}},{"shape_attributes":{"name":"circle","cx":1997,"cy":67,"r":26},"region_attributes":{}},{"shape_attributes":{"name":"circle","cx":1891,"cy":38,"r":28.45},"region_attributes":{}},{"shape_attributes":{"name":"circle","cx":1921,"cy":68,"r":28},"region_attributes":{}},{"shape_attributes":{"name":"circle","cx":2246,"cy":369,"r":25},"region_attributes":{}},{"shape_attributes":{"name":"circle","cx":2258,"cy":329,"r":22},"region_attributes":{}},{"shape_attributes":{"name":"circle","cx":2201,"cy":300,"r":22},"region_attributes":{}},{"shape_attributes":{"name":"circle","cx":2235,"cy":305,"r":20},"region_attributes":{}},{"shape_attributes":{"name":"circle","cx":2517,"cy":119,"r":17.22},"region_attributes":{}},{"shape_attributes":{"name":"circle","cx":2520,"cy":151,"r":17},"region_attributes":{}},{"shape_attributes":{"name":"circle","cx":2540,"cy":135,"r":19},"region_attributes":{}},{"shape_attributes":{"name":"circle","cx":2037,"cy":626,"r":25},"region_attributes":{}},{"shape_attributes":{"name":"circle","cx":2005,"cy":617,"r":26},"region_attributes":{}},{"shape_attributes":{"name":"circle","cx":1918,"cy":551,"r":27},"region_attributes":{}},{"shape_attributes":{"name":"circle","cx":1849,"cy":520,"r":23},"region_attributes":{}},{"shape_attributes":{"name":"circle","cx":3333,"cy":230,"r":39},"region_attributes":{}},{"shape_attributes":{"name":"circle","cx":3301,"cy":249,"r":24},"region_attributes":{}},{"shape_attributes":{"name":"circle","cx":116,"cy":102,"r":28},"region_attributes":{}},{"shape_attributes":{"name":"circle","cx":81,"cy":83,"r":26},"region_attributes":{}},{"shape_attributes":{"name":"circle","cx":96,"cy":117,"r":29},"region_attributes":{}}],"file_attributes":{}}}